github/__init__.py
github/com/__init__.py
github/com/mwitkow/__init__.py
github/com/mwitkow/go_proto_validators/__init__.py
github/com/mwitkow/go_proto_validators/validator_pb2.py
go_proto_validators-0.0.4.dist-info/METADATA
go_proto_validators-0.0.4.dist-info/WHEEL
go_proto_validators-0.0.4.dist-info/top_level.txt
go_proto_validators-0.0.4.dist-info/RECORD
