Metadata-Version: 2.1
Name: go-proto-validators
Version: 0.0.4
Summary: python compile files for https://github.com/mwitkow/go-proto-validators
Home-page: http://supernan1994.github.io/
Author: supernan1994
Author-email: supernan1994@gmail.com
License: UNKNOWN
Platform: UNKNOWN
